odoo/addons/website_sale_product_reference_displayed/README.rst
odoo/addons/website_sale_product_reference_displayed/__init__.py
odoo/addons/website_sale_product_reference_displayed/__manifest__.py
odoo/addons/website_sale_product_reference_displayed/controllers/__init__.py
odoo/addons/website_sale_product_reference_displayed/controllers/variant.py
odoo/addons/website_sale_product_reference_displayed/i18n/ca.po
odoo/addons/website_sale_product_reference_displayed/i18n/es.po
odoo/addons/website_sale_product_reference_displayed/i18n/fr.po
odoo/addons/website_sale_product_reference_displayed/i18n/it.po
odoo/addons/website_sale_product_reference_displayed/i18n/website_sale_product_reference_displayed.pot
odoo/addons/website_sale_product_reference_displayed/readme/CONTRIBUTORS.rst
odoo/addons/website_sale_product_reference_displayed/readme/DESCRIPTION.rst
odoo/addons/website_sale_product_reference_displayed/readme/USAGE.rst
odoo/addons/website_sale_product_reference_displayed/static/description/enable-product-reference.png
odoo/addons/website_sale_product_reference_displayed/static/description/icon.png
odoo/addons/website_sale_product_reference_displayed/static/description/index.html
odoo/addons/website_sale_product_reference_displayed/static/src/js/variant_mixin.js
odoo/addons/website_sale_product_reference_displayed/static/tests/tours/dynamic_variant_reference.js
odoo/addons/website_sale_product_reference_displayed/tests/__init__.py
odoo/addons/website_sale_product_reference_displayed/tests/test_reference_displayed.py
odoo/addons/website_sale_product_reference_displayed/views/assets.xml
odoo/addons/website_sale_product_reference_displayed/views/website_sale_views.xml
odoo14_addon_website_sale_product_reference_displayed-14.0.1.0.1.dev6.dist-info/METADATA
odoo14_addon_website_sale_product_reference_displayed-14.0.1.0.1.dev6.dist-info/WHEEL
odoo14_addon_website_sale_product_reference_displayed-14.0.1.0.1.dev6.dist-info/top_level.txt
odoo14_addon_website_sale_product_reference_displayed-14.0.1.0.1.dev6.dist-info/RECORD
